{
    "/js/app.js": "/js/app.js?id=5f1b27ae110bdaaf9edf",
    "/css/app.css": "/css/app.css?id=9c35af1d3fa1f91d6a05",
    "/css/authorization.css": "/css/authorization.css?id=ddf02607aeaae930ca1d",
    "/css/about.css": "/css/about.css?id=085c0799ca374e81b987",
    "/css/style.css": "/css/style.css?id=84785d3b80cf41461541",
    "/css/home.css": "/css/home.css?id=a87179245982c1c33662",
    "/css/user_profile.css": "/css/user_profile.css?id=c91aedbc2bc30ee50f24",
    "/css/tests.css": "/css/tests.css?id=9a39b84673c146f64b4b",
    "/css/style_test.css": "/css/style_test.css?id=629d01231bb3e53c98e6",
    "/css/style_result.css": "/css/style_result.css?id=2dab212dd8ee78092fab",
    "/css/statistic_table.css": "/css/statistic_table.css?id=6c6e45c80b31df21b78e",
    "/css/contacts.css": "/css/contacts.css?id=4faebfb649772d7f0125",
    "/css/testform.css": "/css/testform.css?id=0f9277357446fcd944a5"
}
